ctrlf/__init__.py
ctrlf/command.py
ctrlf/ts.py
ctrlf-0.0.2.dist-info/METADATA
ctrlf-0.0.2.dist-info/WHEEL
ctrlf-0.0.2.dist-info/entry_points.txt
ctrlf-0.0.2.dist-info/top_level.txt
ctrlf-0.0.2.dist-info/RECORD
