Metadata-Version: 2.1
Name: ctrlf
Version: 0.0.2
Summary: A better solution to find files/directories on your computer uesing their name or regular expression
Home-page: UNKNOWN
Author: theunderdog
Author-email: ahmedbonumstelio@gmail.com
License: UNKNOWN
Platform: UNKNOWN
Classifier: Programming Language :: Python :: 3
Classifier: License :: OSI Approved :: MIT License
Classifier: Operating System :: OS Independent
